_taskdependencygraph_version.py
taskdependencygraph/__init__.py
taskdependencygraph/py.typed
taskdependencygraph/task_dependency_graph.py
taskdependencygraph/models/__init__.py
taskdependencygraph/models/ids.py
taskdependencygraph/models/person.py
taskdependencygraph/models/task_dependency_edge.py
taskdependencygraph/models/task_dependency_update.py
taskdependencygraph/models/task_execution_status.py
taskdependencygraph/models/task_node.py
taskdependencygraph/models/task_node_as_artificial_endnode.py
taskdependencygraph/models/task_node_as_artificial_startnode.py
taskdependencygraph/plotting/__init__.py
taskdependencygraph/plotting/kroki.py
taskdependencygraph/plotting/protocols.py
taskdependencygraph-0.1.0.dist-info/METADATA
taskdependencygraph-0.1.0.dist-info/WHEEL
taskdependencygraph-0.1.0.dist-info/RECORD
