Metadata-Version: 2.4
Name: taskdependencygraph
Version: 0.1.0
Summary: Wrapper around a NetworkX Digraph to model and visualize tasks/todos, their duration and interdependencies
Project-URL: Changelog, https://github.com/Hochfrequenz/task-dependency-graph/releases
Project-URL: Homepage, https://github.com/Hochfrequenz/task-dependency-graph
Author-email: Hochfrequenz Unternehmensberatung GmbH <info+github@hochfrequenz.de>
License: MIT
Keywords: digraph,graph,kroki,networkx,task,task dependency
Classifier: Development Status :: 4 - Beta
Classifier: Environment :: Console
Classifier: Intended Audience :: Developers
Classifier: License :: OSI Approved :: MIT License
Classifier: Operating System :: OS Independent
Classifier: Programming Language :: Python
Classifier: Programming Language :: Python :: 3 :: Only
Classifier: Programming Language :: Python :: 3.11
Classifier: Programming Language :: Python :: 3.12
Classifier: Programming Language :: Python :: 3.13
Requires-Python: >=3.11
Requires-Dist: aiohttp
Requires-Dist: networkx
Requires-Dist: pydantic-settings
Requires-Dist: pydantic[email]>=2
Provides-Extra: coverage
Requires-Dist: coverage==7.6.12; extra == 'coverage'
Provides-Extra: dev
Requires-Dist: pip-tools; extra == 'dev'
Provides-Extra: formatting
Requires-Dist: black==25.1.0; extra == 'formatting'
Requires-Dist: isort==6.0.1; extra == 'formatting'
Provides-Extra: linting
Requires-Dist: pylint==3.3.4; extra == 'linting'
Provides-Extra: packaging
Requires-Dist: build==1.2.2.post1; extra == 'packaging'
Requires-Dist: twine==6.1.0; extra == 'packaging'
Provides-Extra: spell-check
Requires-Dist: codespell==2.4.1; extra == 'spell-check'
Provides-Extra: tests
Requires-Dist: pytest-asyncio==0.21.2; extra == 'tests'
Requires-Dist: pytest==8.3.5; extra == 'tests'
Requires-Dist: testcontainers; extra == 'tests'
Provides-Extra: type-check
Requires-Dist: mypy==1.15.0; extra == 'type-check'
Requires-Dist: types-docker; extra == 'type-check'
